<shapes>
<shape aspect="variable" centered="False" h="48" name="APT (Aptamer)" strokewidth="inherit" w="48">
    <connections />
    <foreground>
        <strokewidth width="2.88" />
        <path>
            <move x="19.41605301914581" y="48.0" />
            <line x="19.41605301914581" y="35.220176730486" />
            <curve x1="23.01693667157584" x2="25.6678939617084" x3="25.6678939617084" y1="34.292341678939614" y2="31.04491899852725" y3="27.156848306332826" />
            <curve x1="25.6678939617084" x2="25.54639175257731" x3="25.303387334315165" y1="26.306332842415316" y2="25.48895434462444" y3="24.71575846833578" />
            <line x="32.86966126656848" y="20.35272459499262" />
            <curve x1="33.45508100147276" x2="34.1178203240059" x3="34.83578792341679" y1="20.67304860088366" y2="20.871870397643576" y3="20.871870397643576" />
            <curve x1="37.133284241531676" x2="39.0" x3="39.0" y1="20.871870397643576" y2="19.005154639175256" y3="16.69661266568482" />
            <curve x1="39.0" x2="37.133284241531676" x3="34.83578792341679" y1="14.399116347569958" y2="12.532400589101613" y3="12.532400589101613" />
            <curve x1="32.52724594992637" x2="30.660530191458037" x3="30.660530191458037" y1="12.532400589101613" y2="14.399116347569958" y3="16.69661266568482" />
            <curve x1="30.660530191458037" x2="30.67157584683359" x3="30.67157584683359" y1="16.740795287187034" y2="16.77393225331368" y3="16.807069219440347" />
            <line x="23.127393225331364" y="21.170103092783496" />
            <curve x1="21.625184094256248" x2="19.581737849779074" x3="17.339469808541985" y1="19.723122238586136" y2="18.828424153166424" y3="18.828424153166424" />
            <curve x1="12.733431516936687" x2="9.0" x3="9.0" y1="18.828424153166424" y2="22.55081001472754" y3="27.156848306332826" />
            <curve x1="9.0" x2="11.662002945508089" x3="15.25184094256258" y1="31.04491899852725" y2="34.292341678939614" y3="35.220176730486" />
            <line x="15.25184094256258" y="48.0" />
        </path>
      <fillstroke />
    </foreground>
</shape>
</shapes>